<?xml version="1.0" encoding="UTF-8"?>
<MetaDataObject xmlns="http://v8.1c.ru/8.3/MDClasses" xmlns:app="http://v8.1c.ru/8.2/managed-application/core" xmlns:cfg="http://v8.1c.ru/8.1/data/enterprise/current-config" xmlns:cmi="http://v8.1c.ru/8.2/managed-application/cmi" xmlns:ent="http://v8.1c.ru/8.1/data/enterprise" xmlns:lf="http://v8.1c.ru/8.2/managed-application/logform" xmlns:style="http://v8.1c.ru/8.1/data/ui/style" xmlns:sys="http://v8.1c.ru/8.1/data/ui/fonts/system" xmlns:v8="http://v8.1c.ru/8.1/data/core" xmlns:v8ui="http://v8.1c.ru/8.1/data/ui" xmlns:web="http://v8.1c.ru/8.1/data/ui/colors/web" xmlns:win="http://v8.1c.ru/8.1/data/ui/colors/windows" xmlns:xen="http://v8.1c.ru/8.3/xcf/enums" xmlns:xpr="http://v8.1c.ru/8.3/xcf/predef" xmlns:xr="http://v8.1c.ru/8.3/xcf/readable" xmlns:xs="http://www.w3.org/2001/XMLSchema" xmlns:xsi="http://www.w3.org/2001/XMLSchema-instance" version="2.14">
	<DefinedType uuid="e15c4450-e65c-4ede-a87e-d8dc20f9742c">
		<InternalInfo>
			<xr:GeneratedType name="DefinedType.typePresentation" category="DefinedType">
				<xr:TypeId>bb55dbec-f7ba-4ab5-b22f-89a976a92f1a</xr:TypeId>
				<xr:ValueId>e4468c2e-05bb-43af-a16f-ac1ec7ec8020</xr:ValueId>
			</xr:GeneratedType>
		</InternalInfo>
		<Properties>
			<Name>typePresentation</Name>
			<Synonym>
				<v8:item>
					<v8:lang>de</v8:lang>
					<v8:content>Typ Präsentation</v8:content>
				</v8:item>
				<v8:item>
					<v8:lang>tr</v8:lang>
					<v8:content>Tip görünüm</v8:content>
				</v8:item>
				<v8:item>
					<v8:lang>en</v8:lang>
					<v8:content>Type presentation</v8:content>
				</v8:item>
				<v8:item>
					<v8:lang>fr</v8:lang>
					<v8:content>Type Présentation</v8:content>
				</v8:item>
				<v8:item>
					<v8:lang>ru</v8:lang>
					<v8:content>Тип представление</v8:content>
				</v8:item>
			</Synonym>
			<Comment/>
			<Type>
				<v8:Type>cfg:CatalogManager.ItemTypes</v8:Type>
				<v8:Type>cfg:CatalogManager.PriceTypes</v8:Type>
				<v8:Type>cfg:CatalogManager.AddAttributeAndPropertySets</v8:Type>
				<v8:Type>cfg:CatalogManager.CashAccounts</v8:Type>
				<v8:Type>cfg:CatalogManager.AddAttributeAndPropertyValues</v8:Type>
				<v8:Type>cfg:CatalogManager.ItemSegments</v8:Type>
				<v8:Type>cfg:CatalogManager.PaymentTypes</v8:Type>
				<v8:Type>cfg:CatalogManager.TaxRates</v8:Type>
				<v8:Type>cfg:CatalogManager.Items</v8:Type>
				<v8:Type>cfg:CatalogManager.SpecialOffers</v8:Type>
				<v8:Type>cfg:CatalogManager.Stores</v8:Type>
				<v8:Type>cfg:CatalogManager.Countries</v8:Type>
				<v8:Type>cfg:CatalogManager.Partners</v8:Type>
				<v8:Type>cfg:CatalogManager.Companies</v8:Type>
				<v8:Type>cfg:CatalogManager.Currencies</v8:Type>
			</Type>
		</Properties>
	</DefinedType>
</MetaDataObject>