<?xml version="1.0" encoding="UTF-8"?>
<MetaDataObject xmlns="http://v8.1c.ru/8.3/MDClasses" xmlns:app="http://v8.1c.ru/8.2/managed-application/core" xmlns:cfg="http://v8.1c.ru/8.1/data/enterprise/current-config" xmlns:cmi="http://v8.1c.ru/8.2/managed-application/cmi" xmlns:ent="http://v8.1c.ru/8.1/data/enterprise" xmlns:lf="http://v8.1c.ru/8.2/managed-application/logform" xmlns:style="http://v8.1c.ru/8.1/data/ui/style" xmlns:sys="http://v8.1c.ru/8.1/data/ui/fonts/system" xmlns:v8="http://v8.1c.ru/8.1/data/core" xmlns:v8ui="http://v8.1c.ru/8.1/data/ui" xmlns:web="http://v8.1c.ru/8.1/data/ui/colors/web" xmlns:win="http://v8.1c.ru/8.1/data/ui/colors/windows" xmlns:xen="http://v8.1c.ru/8.3/xcf/enums" xmlns:xpr="http://v8.1c.ru/8.3/xcf/predef" xmlns:xr="http://v8.1c.ru/8.3/xcf/readable" xmlns:xs="http://www.w3.org/2001/XMLSchema" xmlns:xsi="http://www.w3.org/2001/XMLSchema-instance" version="2.14">
	<DefinedType uuid="b30fffbf-e813-44ed-bf08-069ab8d3913f">
		<InternalInfo>
			<xr:GeneratedType name="DefinedType.typeBarcode" category="DefinedType">
				<xr:TypeId>c23154ca-d846-4adb-b794-5385974f0ff4</xr:TypeId>
				<xr:ValueId>f70f12af-8f69-4727-a2aa-65666af105d7</xr:ValueId>
			</xr:GeneratedType>
		</InternalInfo>
		<Properties>
			<Name>typeBarcode</Name>
			<Synonym>
				<v8:item>
					<v8:lang>de</v8:lang>
					<v8:content>Typ Barcode</v8:content>
				</v8:item>
				<v8:item>
					<v8:lang>tr</v8:lang>
					<v8:content>Tip barkod</v8:content>
				</v8:item>
				<v8:item>
					<v8:lang>en</v8:lang>
					<v8:content>Type barcode</v8:content>
				</v8:item>
				<v8:item>
					<v8:lang>fr</v8:lang>
					<v8:content>Type Code-barres</v8:content>
				</v8:item>
				<v8:item>
					<v8:lang>ru</v8:lang>
					<v8:content>Тип штрихкода</v8:content>
				</v8:item>
			</Synonym>
			<Comment/>
			<Type>
				<v8:Type>xs:string</v8:Type>
				<v8:StringQualifiers>
					<v8:Length>64</v8:Length>
					<v8:AllowedLength>Variable</v8:AllowedLength>
				</v8:StringQualifiers>
			</Type>
		</Properties>
	</DefinedType>
</MetaDataObject>